c8utils/__init__.py
c8utils/fgcolors.py
c8utils/messages.py
c8utils-0.0.1.dist-info/LICENSE
c8utils-0.0.1.dist-info/METADATA
c8utils-0.0.1.dist-info/WHEEL
c8utils-0.0.1.dist-info/top_level.txt
c8utils-0.0.1.dist-info/RECORD
