Metadata-Version: 2.1
Name: c8utils
Version: 0.0.1
Summary: add some colour to text
Author-email: "(AA)" <adam@a6n.net>
Project-URL: Homepage, http://not.available.yet
Classifier: Programming Language :: Python :: 3
Classifier: License :: OSI Approved :: MIT License
Classifier: Operating System :: OS Independent
Requires-Python: >=3.8
License-File: LICENSE
